<?xml version="1.0" encoding="UTF-8"?>
<resources xmlns:xliff="urn:oasis:names:tc:xliff:document:1.2">
<string name="ugif_edit_text_edit_editor">"Изменить"</string>
<string name="ugif_edit_text_edit_effect">"Эффект"</string>
<string name="ugif_edit_text_edit_photoframe">"Рамка"</string>
<string name="ugif_edit_text_edit_texture">"Текстура"</string>
<string name="ugif_edit_text_edit_play_speed">"Скорость"</string>
<string name="ugif_edit_text_edit_play_mode">"Режим"</string>
<string name="ugif_edit_text_waiting">"Подождите…"</string>
<string name="ugif_edit_choose_error_image_one">"Одно изображение повреждено"</string>
<string name="ugif_edit_choose_error_image_many">"<xliff:g id="NUM">%s</xliff:g> изображений повреждено"</string>
<string name="ugif_edit_open_error_image">"Не удается загрузить изображение"</string>
<string name="ugif_edit_compose_edit_tips">"Оставьте как минимум 2 фотографии, чтобы скомбинировать"</string>
<string name="ugif_edit_composing_tips">"GIF скомбинирован"</string>
<string name="ugif_edit_composing_failed_tips">"Не удалось скомбинировать GIF"</string>
<string name="ugif_edit_operation_memory_low_warn">"Доступная память системы является слишком низкой,пожалуйста, прежде всего освободить память"</string>
<string name="text_edit_playspeed_slow">"Медленная"</string>
<string name="text_edit_playspeed_normal">"Обычный"</string>
<string name="text_edit_playspeed_fast">"Быстрая"</string>
<string name="ugif_edit_text_effect_skin">"Кожа"</string>
<string name="ugif_edit_text_effect_lightcolor">"Светлая"</string>
<string name="ugif_edit_text_effect_sketch">"Набросок"</string>
<string name="ugif_edit_text_effect_colorfull">"Разноцветный"</string>
<string name="ugif_edit_text_effect_funny">"Забавный"</string>
<string name="ugif_edit_text_effect_nostalgia">"Ностальгия"</string>
<string name="ugif_edit_text_effect_bw">"Ч &amp; Б"</string>
<string name="ugif_edit_text_effect_deform">"Деформированный"</string>
<string name="ugif_text_edit_exit_tip_title">Варинг...</string>
<string name="ugif_text_edit_exit_tip_message">"Изображение не сохранено. Вы действительно хотите выйти?"</string>
<string name="ugif_text_edit_exit_tip_save">"Сохранить"</string>
<string name="ugif_text_edit_exit_tip_exit">"Выход"</string>
<string name="ugif_text_edit_exit_tip_cancel">Отмена</string>
<string name="local_gif_collection">"Локальный GIF"</string>
<string name="pref_gif_settings_category">"Настройки GIF"</string>
<string name="pref_camera_review_del">"Уверены, что хотите удалить эту фотографию?"</string>
<string name="gif_play_first_gif_tips">"Это первый GIF"</string>
<string name="gif_compose_edit_tips">"Оставьте как минимум 2 фотографии, чтобы скомбинировать"</string>
</resources>
