<?xml version="1.0" encoding="UTF-8"?>
<resources xmlns:xliff="urn:oasis:names:tc:xliff:document:1.2">
<string name="ugif_edit_text_edit_editor">"ફેરફાર"</string>
<string name="ugif_edit_text_edit_effect">“અસર”</string>
<string name="ugif_edit_text_edit_photoframe">"ફ્રેમ"</string>
<string name="ugif_edit_text_edit_texture">"ટેક્સચર"</string>
<string name="ugif_edit_text_edit_play_speed">"ઝડપ"</string>
<string name="ugif_edit_text_edit_play_mode">"મૉડ"</string>
<string name="ugif_edit_text_waiting">કૃપા કરી પ્રતિક્ષા કરો\u2026</string>
<string name="ugif_edit_choose_error_image_one">"એક નુકસાન ચિત્ર છે"</string>
<string name="ugif_edit_choose_error_image_many">"ત્યાં <xliff:g id="NUM">%s</xliff:g> નુકશાન ચિત્રો"</string>
<string name="ugif_edit_open_error_image">"છબી લોડ થઈ શકશે નહિ"</string>
<string name="ugif_edit_compose_edit_tips">"ઓછામાં ઓછા બે ચિત્રો કંપોઝ કરવા માટે બાકી રાખો"</string>
<string name="ugif_edit_composing_tips">"GIF કંપોઝ થઇ ગઈ છે"</string>
<string name="ugif_edit_composing_failed_tips">"GIF કંપોઝ નિષ્ફળ"</string>
<string name="ugif_edit_operation_memory_low_warn">"સિસ્ટમ ની  ઉપલબ્ધ મેમરી ખૂબ ઓછી છે, કૃપા કરી પહેલા છોડો"</string>
<string name="text_edit_playspeed_slow">ધીમું</string>
<string name="text_edit_playspeed_normal">"સામાન્ય"</string>
<string name="text_edit_playspeed_fast">ઝડપી</string>
<string name="ugif_edit_text_effect_skin">"સ્કીન"</string>
<string name="ugif_edit_text_effect_lightcolor">"આછું"</string>
<string name="ugif_edit_text_effect_sketch">"સ્કેચ"</string>
<string name="ugif_edit_text_effect_colorfull">"સંપૂર્ણ રંગ"</string>
<string name="ugif_edit_text_effect_funny">"રમુજી"</string>
<string name="ugif_edit_text_effect_nostalgia">"નોસ્ટાલ્જિયા"</string>
<string name="ugif_edit_text_effect_bw">"કાળું &amp; સફેદ"</string>
<string name="ugif_edit_text_effect_deform">"બેડોળ"</string>
<string name="ugif_text_edit_exit_tip_title">ચેતવણી </string>
<string name="ugif_text_edit_exit_tip_message">""છબી સાચવી નથી, તમે બહાર નીકળવા માટે ખાતરી કરો છો?" "</string>
<string name="ugif_text_edit_exit_tip_save">"બચાવો"</string>
<string name="ugif_text_edit_exit_tip_exit">"નિર્ગમન"</string>
<string name="ugif_text_edit_exit_tip_cancel">"રદ્દ"</string>
<string name="local_gif_collection">"સ્થાનિક GIF"</string>
<string name="pref_gif_settings_category">"GIF સેટિંગ્સ"</string>
<string name="pref_camera_review_del">"શું ખરેખ તમારે આ પિક્ચર ડિલીટ કરવું છે?"</string>
<string name="gif_play_first_gif_tips">"આ પ્રથમ GIF છે"</string>
<string name="gif_compose_edit_tips">"ઓછામાં ઓછા બે ચિત્રો કંપોઝ કરવા માટે બાકી રાખો"</string>
</resources>
